heart_slicer/__init__.py
heart_slicer/common.py
heart_slicer/diagram.py
heart_slicer/main.py
heart_slicer/slice_analyser.py
heart_slicer/slicer.py
heart_slicer/__pycache__/__init__.cpython-311.pyc
heart_slicer/__pycache__/__init__.cpython-313.pyc
heart_slicer/__pycache__/common.cpython-311.pyc
heart_slicer/__pycache__/common.cpython-313.pyc
heart_slicer/__pycache__/heart.cpython-311.pyc
heart_slicer/__pycache__/main.cpython-311.pyc
heart_slicer/__pycache__/main.cpython-313.pyc
heart_slicer/__pycache__/slice_analyser.cpython-311.pyc
heart_slicer/__pycache__/slice_analyser.cpython-313.pyc
heart_slicer/__pycache__/slicer.cpython-311.pyc
heart_slicer/__pycache__/slicer.cpython-313.pyc
heart_slicer-0.2.0.dist-info/METADATA
heart_slicer-0.2.0.dist-info/WHEEL
heart_slicer-0.2.0.dist-info/top_level.txt
heart_slicer-0.2.0.dist-info/RECORD
