Metadata-Version: 2.2
Name: heart_slicer
Version: 0.2.0
Summary: A package to process images of coloured histology sections of the heart for analyses.
Author: True Galaxus
Author-email: truegalaxus@gmail.com
Classifier: Development Status :: 2 - Pre-Alpha
Classifier: Programming Language :: Python :: 3.11
Requires-Dist: numpy
Requires-Dist: pillow
Requires-Dist: pyyaml
Requires-Dist: matplotlib
Dynamic: author
Dynamic: author-email
Dynamic: classifier
Dynamic: description
Dynamic: description-content-type
Dynamic: requires-dist
Dynamic: summary
